Metadata-Version: 1.1
Name: ar-crm-groups
Version: 0.0.74
Summary: Your project description goes here
Home-page: https://github.com/arteria/ar-crm-groups
Author: arteria GmbH
Author-email: admin@arteria.ch
License: BSD
Keywords: ar-crm-groups
Platform: UNKNOWN
Classifier: Development Status :: 2 - Pre-Alpha
Classifier: Framework :: Django
Classifier: Intended Audience :: Developers
Classifier: License :: OSI Approved :: BSD License
Classifier: Natural Language :: English
Classifier: Programming Language :: Python :: 2
Classifier: Programming Language :: Python :: 2.6
Classifier: Programming Language :: Python :: 2.7
Classifier: Programming Language :: Python :: 3
Classifier: Programming Language :: Python :: 3.3
